hfautogen/__init__.py
hfautogen/hfautogen.py
hfautogen-1.10.dist-info/LICENSE
hfautogen-1.10.dist-info/METADATA
hfautogen-1.10.dist-info/WHEEL
hfautogen-1.10.dist-info/top_level.txt
hfautogen-1.10.dist-info/RECORD
