Metadata-Version: 2.1
Name: hfautogen
Version: 1.10
Summary: HuggingFace Integration with Microsoft's Autogen
Home-page: https://github.com/Solonce/HFAutogen
Author: Solomon Ince
Author-email: Solomon Ince <solomon@solonce.com>
License: MIT License
Classifier: Programming Language :: Python :: 3
Classifier: License :: OSI Approved :: MIT License
Classifier: Operating System :: OS Independent
Requires-Python: >=3.6
License-File: LICENSE
Requires-Dist: openai ==1.12.0
Requires-Dist: transformers ==4.38.0
Requires-Dist: pyautogen ==0.2.10
